pm_transcript_metang/__init__.py
pm_transcript_metang/tools/__init__.py
pm_transcript_metang/tools/load_transcript_tool.py
pm_transcript_metang/tools/utils.py
pm_transcript_metang/yamls/load_transcript_tool.yaml
tests/__init__.py
tests/test_load_transcript_tool.py
pm_transcript_metang-0.0.1.dist-info/METADATA
pm_transcript_metang-0.0.1.dist-info/WHEEL
pm_transcript_metang-0.0.1.dist-info/entry_points.txt
pm_transcript_metang-0.0.1.dist-info/top_level.txt
pm_transcript_metang-0.0.1.dist-info/RECORD
