Metadata-Version: 2.1
Name: pm-transcript-metang
Version: 0.0.1
Summary: This is my tools package
